.gitignore
LICENSE
README.md
runtests.py
setup.cfg
setup.py
m4/__init__.py
parse_m4.egg-info/PKG-INFO
parse_m4.egg-info/SOURCES.txt
parse_m4.egg-info/dependency_links.txt
parse_m4.egg-info/top_level.txt
test/changequote.in
test/changequote.out
test/changequote_doublequote.in
test/changequote_doublequote.out
test/comment.in
test/comment.out
test/define.in
test/define.out
test/divert.in
test/divert.out
test/dnl.in
test/dnl.out
test/nested_quotes.in
test/nested_quotes.out
test/quote.in
test/quote.out